{"multiStageQuery":{"type":"multiStageQuery","taskId":"query-3986b98a-9a97-4a14-bb23-d86ebcbd6f54","payload":{"status":{"status":"FAILED","errorReport":{"taskId":"query-3986b98a-9a97-4a14-bb23-d86ebcbd6f54-worker0_0","host":"localhost:8101","stageNumber":0,"error":{"errorCode":"UnknownError","message":"java.lang.RuntimeException: org.apache.druid.java.util.common.ISE: namespace [JdbcExtractionNamespace{connectorConfig=DbConnectorConfig{createTables=true, connectURI='jdbc:postgresql://localhost:5432/druid', user='druid', passwordProvider=org.apache.druid.metadata.DefaultPasswordProvider, dbcpProperties=null}, table='rollnumberlookup', keyColumn='name', valueColumn='rollnumber', tsColumn='timeColumn', filter='null', pollPeriod=PT1M, jitterSeconds=0, loadTimeoutSeconds=120, maxHeapPercentage=10}] : org.apache.druid.server.lookup.namespace.cache.CacheScheduler$EntryImpl@5b7abfd8: CACHE_NOT_INITIALIZED, extractorID = namespace-factory-JdbcExtractionNamespace{connectorConfig=DbConnectorConfig{createTables=true, connectURI='jdbc:postgresql://localhost:5432/druid', user='druid', passwordProvider=org.apache.druid.metadata.DefaultPasswordProvider, dbcpProperties=null}, table='rollnumberlookup', keyColumn='name', valueColumn='rollnumber', tsColumn='timeColumn', filter='null', pollPeriod=PT1M, jitterSeconds=0, loadTimeoutSeconds=120, maxHeapPercentage=10}-1b78eb3f-4f4c-4a49-94e1-d29f8b9c2626","errorMessage":"java.lang.RuntimeException: org.apache.druid.java.util.common.ISE: namespace [JdbcExtractionNamespace{connectorConfig=DbConnectorConfig{createTables=true, connectURI='jdbc:postgresql://localhost:5432/druid', user='druid', passwordProvider=org.apache.druid.metadata.DefaultPasswordProvider, dbcpProperties=null}, table='rollnumberlookup', keyColumn='name', valueColumn='rollnumber', tsColumn='timeColumn', filter='null', pollPeriod=PT1M, jitterSeconds=0, loadTimeoutSeconds=120, maxHeapPercentage=10}] : org.apache.druid.server.lookup.namespace.cache.CacheScheduler$EntryImpl@5b7abfd8: CACHE_NOT_INITIALIZED, extractorID = namespace-factory-JdbcExtractionNamespace{connectorConfig=DbConnectorConfig{createTables=true, connectURI='jdbc:postgresql://localhost:5432/druid', user='druid', passwordProvider=org.apache.druid.metadata.DefaultPasswordProvider, dbcpProperties=null}, table='rollnumberlookup', keyColumn='name', valueColumn='rollnumber', tsColumn='timeColumn', filter='null', pollPeriod=PT1M, jitterSeconds=0, loadTimeoutSeconds=120, maxHeapPercentage=10}-1b78eb3f-4f4c-4a49-94e1-d29f8b9c2626"},"exceptionStackTrace":"java.lang.RuntimeException: org.apache.druid.java.util.common.ISE: namespace [JdbcExtractionNamespace{connectorConfig=DbConnectorConfig{createTables=true, connectURI='jdbc:postgresql://localhost:5432/druid', user='druid', passwordProvider=org.apache.druid.metadata.DefaultPasswordProvider, dbcpProperties=null}, table='rollnumberlookup', keyColumn='name', valueColumn='rollnumber', tsColumn='timeColumn', filter='null', pollPeriod=PT1M, jitterSeconds=0, loadTimeoutSeconds=120, maxHeapPercentage=10}] : org.apache.druid.server.lookup.namespace.cache.CacheScheduler$EntryImpl@5b7abfd8: CACHE_NOT_INITIALIZED, extractorID = namespace-factory-JdbcExtractionNamespace{connectorConfig=DbConnectorConfig{createTables=true, connectURI='jdbc:postgresql://localhost:5432/druid', user='druid', passwordProvider=org.apache.druid.metadata.DefaultPasswordProvider, dbcpProperties=null}, table='rollnumberlookup', keyColumn='name', valueColumn='rollnumber', tsColumn='timeColumn', filter='null', pollPeriod=PT1M, jitterSeconds=0, loadTimeoutSeconds=120, maxHeapPercentage=10}-1b78eb3f-4f4c-4a49-94e1-d29f8b9c2626\n\tat org.apache.druid.java.util.common.Either.valueOrThrow(Either.java:95)\n\tat org.apache.druid.frame.processor.FrameProcessorExecutor$1ExecutorRunnable.runProcessorNow(FrameProcessorExecutor.java:259)\n\tat org.apache.druid.frame.processor.FrameProcessorExecutor$1ExecutorRunnable.run(FrameProcessorExecutor.java:138)\n\tat org.apache.druid.msq.exec.WorkerImpl$1$2.run(WorkerImpl.java:836)\n\tat java.base/java.util.concurrent.Executors$RunnableAdapter.call(Executors.java:515)\n\tat java.base/java.util.concurrent.FutureTask.run(FutureTask.java:264)\n\tat org.apache.druid.query.PrioritizedListenableFutureTask.run(PrioritizedExecutorService.java:259)\n\tat java.base/java.util.concurrent.ThreadPoolExecutor.runWorker(ThreadPoolExecutor.java:1128)\n\tat java.base/java.util.concurrent.ThreadPoolExecutor$Worker.run(ThreadPoolExecutor.java:628)\n\tat java.base/java.lang.Thread.run(Thread.java:829)\nCaused by: org.apache.druid.java.util.common.ISE: namespace [JdbcExtractionNamespace{connectorConfig=DbConnectorConfig{createTables=true, connectURI='jdbc:postgresql://localhost:5432/druid', user='druid', passwordProvider=org.apache.druid.metadata.DefaultPasswordProvider, dbcpProperties=null}, table='rollnumberlookup', keyColumn='name', valueColumn='rollnumber', tsColumn='timeColumn', filter='null', pollPeriod=PT1M, jitterSeconds=0, loadTimeoutSeconds=120, maxHeapPercentage=10}] : org.apache.druid.server.lookup.namespace.cache.CacheScheduler$EntryImpl@5b7abfd8: CACHE_NOT_INITIALIZED, extractorID = namespace-factory-JdbcExtractionNamespace{connectorConfig=DbConnectorConfig{createTables=true, connectURI='jdbc:postgresql://localhost:5432/druid', user='druid', passwordProvider=org.apache.druid.metadata.DefaultPasswordProvider, dbcpProperties=null}, table='rollnumberlookup', keyColumn='name', valueColumn='rollnumber', tsColumn='timeColumn', filter='null', pollPeriod=PT1M, jitterSeconds=0, loadTimeoutSeconds=120, maxHeapPercentage=10}-1b78eb3f-4f4c-4a49-94e1-d29f8b9c2626\n\tat org.apache.druid.query.lookup.NamespaceLookupExtractorFactory.get(NamespaceLookupExtractorFactory.java:227)\n\tat org.apache.druid.query.lookup.NamespaceLookupExtractorFactory.get(NamespaceLookupExtractorFactory.java:43)\n\tat org.apache.druid.query.lookup.LookupSegment.lambda$new$0(LookupSegment.java:52)\n\tat org.apache.druid.java.util.common.guava.SimpleSequence$1.make(SimpleSequence.java:39)\n\tat org.apache.druid.java.util.common.guava.BaseSequence.toYielder(BaseSequence.java:66)\n\tat org.apache.druid.java.util.common.guava.Yielders.each(Yielders.java:32)\n\tat org.apache.druid.segment.RowWalker.<init>(RowWalker.java:53)\n\tat org.apache.druid.segment.RowBasedStorageAdapter.makeCursors(RowBasedStorageAdapter.java:195)\n\tat org.apache.druid.msq.querykit.scan.ScanQueryFrameProcessor.makeCursors(ScanQueryFrameProcessor.java:445)\n\tat org.apache.druid.msq.querykit.scan.ScanQueryFrameProcessor.runWithSegment(ScanQueryFrameProcessor.java:261)\n\tat org.apache.druid.msq.querykit.BaseLeafFrameProcessor.runIncrementally(BaseLeafFrameProcessor.java:88)\n\tat org.apache.druid.msq.querykit.scan.ScanQueryFrameProcessor.runIncrementally(ScanQueryFrameProcessor.java:162)\n\tat org.apache.druid.frame.processor.FrameProcessors$1FrameProcessorWithBaggage.runIncrementally(FrameProcessors.java:75)\n\tat org.apache.druid.frame.processor.FrameProcessorExecutor$1ExecutorRunnable.runProcessorNow(FrameProcessorExecutor.java:230)\n\t... 8 more\n"},"startTime":"2024-04-17T11:53:13.613Z","durationMs":14113,"workers":{"0":[{"workerId":"query-3986b98a-9a97-4a14-bb23-d86ebcbd6f54-worker0_0","state":"FAILED","durationMs":13615,"pendingMs":108}]},"pendingTasks":0,"runningTasks":1},"stages":[{"stageNumber":0,"definition":{"id":"query-3986b98a-9a97-4a14-bb23-d86ebcbd6f54_0","input":[{"type":"LookupInputSpec","lookupName":"rollnumberlookup"}],"processor":{"type":"scan","query":{"queryType":"scan","dataSource":{"type":"lookup","lookup":"rollnumberlookup"},"intervals":{"type":"intervals","intervals":["-146136543-09-08T08:23:32.096Z/146140482-04-24T15:36:27.903Z"]},"resultFormat":"compactedList","limit":1001,"columns":["k","v"],"legacy":false,"context":{"__resultFormat":"array","__user":"allowAll","executionMode":"async","finalize":true,"maxNumTasks":2,"maxParseExceptions":0,"queryId":"3986b98a-9a97-4a14-bb23-d86ebcbd6f54","scanSignature":"[{\"name\":\"k\",\"type\":\"STRING\"},{\"name\":\"v\",\"type\":\"STRING\"}]","sqlOuterLimit":1001,"sqlQueryId":"3986b98a-9a97-4a14-bb23-d86ebcbd6f54","sqlStringifyArrays":false},"columnTypes":["STRING","STRING"],"granularity":{"type":"all"}}},"signature":[{"name":"k","type":"STRING"},{"name":"v","type":"STRING"}],"shuffleSpec":{"type":"mix"},"maxWorkerCount":1},"workerCount":1,"partitionCount":1,"startTime":"2024-04-17T11:53:13.757Z","duration":13969},{"stageNumber":1,"definition":{"id":"query-3986b98a-9a97-4a14-bb23-d86ebcbd6f54_1","input":[{"type":"stage","stage":0}],"processor":{"type":"limit","limit":1001},"signature":[{"name":"k","type":"STRING"},{"name":"v","type":"STRING"}],"maxWorkerCount":1}}],"counters":{"0":{"0":{}}}}}}